{"type":"FeatureCollection","name":"signal detections","features":[{"type":"Feature","properties":{"REMARKS":""},"geometry":{"type":"Point","coordinates":[144.78296107010243,13.413179321818403,148.10458252670654]}},{"type":"Feature","properties":{"REMARKS":""},"geometry":{"type":"Point","coordinates":[144.78326585843655,13.413337084278593,148.43369533570169]}},{"type":"Feature","properties":{"REMARKS":"tree 1"},"geometry":{"type":"Point","coordinates":[144.78338807114616,13.412757787033108,146.7087978098463]}},{"type":"Feature","properties":{"REMARKS":"tree 2"},"geometry":{"type":"Point","coordinates":[144.78329930266372,13.412733890073952,146.7449127332312]}},{"type":"Feature","properties":{"REMARKS":"tree 3"},"geometry":{"type":"Point","coordinates":[144.78324590070466,13.41275738099899,146.8098847191227]}},{"type":"Feature","properties":{"REMARKS":""},"geometry":{"type":"Point","coordinates":[144.78207660610073,13.412728423985866,147.32418843575275]}},{"type":"Feature","properties":{"REMARKS":""},"geometry":{"type":"Point","coordinates":[144.7828152684581,13.412505950579089,146.51379593905045]}}]}